mod_manager/__about__.py
mod_manager/__init__.py
mod_manager/__main__.py
mod_manager/algorithms.py
mod_manager/exceptions.py
mod_manager/download_helpers/__init__.py
mod_manager/t_api/__init__.py
mod_manager-2.5.0.dist-info/METADATA
mod_manager-2.5.0.dist-info/WHEEL
mod_manager-2.5.0.dist-info/entry_points.txt
mod_manager-2.5.0.dist-info/licenses/LICENSE.txt
mod_manager-2.5.0.dist-info/RECORD
