Metadata-Version: 2.3
Name: mod-manager
Version: 2.5.0
Project-URL: Documentation, https://github.com/Lumesque/mod-manager#readme
Project-URL: Issues, https://github.com/Lumesque/mod-manager/issues
Project-URL: Source, https://github.com/Lumesque/mod-manager
Author-email: Joshua Luckie <luckie.joshua.c@gmail.com>
License-Expression: MIT
License-File: LICENSE.txt
Classifier: Development Status :: 4 - Beta
Classifier: Programming Language :: Python
Classifier: Programming Language :: Python :: 3.8
Classifier: Programming Language :: Python :: 3.9
Classifier: Programming Language :: Python :: 3.10
Classifier: Programming Language :: Python :: 3.11
Classifier: Programming Language :: Python :: 3.12
Classifier: Programming Language :: Python :: Implementation :: CPython
Classifier: Programming Language :: Python :: Implementation :: PyPy
Requires-Python: >=3.8
Requires-Dist: click
Requires-Dist: requests
